kijpatcher/__init__.py
kijpatcher/__main__.py
kijpatcher/kijpatcher.py
kijpatcher-1.0.0.dist-info/licenses/LICENSE
kijpatcher-1.0.0.dist-info/METADATA
kijpatcher-1.0.0.dist-info/WHEEL
kijpatcher-1.0.0.dist-info/entry_points.txt
kijpatcher-1.0.0.dist-info/top_level.txt
kijpatcher-1.0.0.dist-info/RECORD
