Metadata-Version: 2.4
Name: kijpatcher
Version: 1.0.0
Summary: A CLI tool to Patch KiCad-generated gerber file to complies with JLC rules.
Author-email: Xina <realxinaovo@gmail.com>
License-Expression: GPL-2.0-only
Requires-Python: >=3.7
License-File: LICENSE
Dynamic: license-file
